types_webob-1.8.0.20250820.dist-info/licenses/LICENSE
webob-stubs/METADATA.toml
webob-stubs/__init__.pyi
webob-stubs/_types.pyi
webob-stubs/acceptparse.pyi
webob-stubs/byterange.pyi
webob-stubs/cachecontrol.pyi
webob-stubs/client.pyi
webob-stubs/compat.pyi
webob-stubs/cookies.pyi
webob-stubs/datetime_utils.pyi
webob-stubs/dec.pyi
webob-stubs/descriptors.pyi
webob-stubs/etag.pyi
webob-stubs/exc.pyi
webob-stubs/headers.pyi
webob-stubs/multidict.pyi
webob-stubs/py.typed
webob-stubs/request.pyi
webob-stubs/response.pyi
webob-stubs/static.pyi
webob-stubs/util.pyi
types_webob-1.8.0.20250820.dist-info/METADATA
types_webob-1.8.0.20250820.dist-info/WHEEL
types_webob-1.8.0.20250820.dist-info/top_level.txt
types_webob-1.8.0.20250820.dist-info/RECORD
